[
  {
    "id": 1,
    "titulo": "RECEPCIÓN DE PASES",
    "categoria": "Pases",
    "image": "./assets/img/video.png",
    "descripcion": "En este video se explica como recibir pases de expediente remitidos por otras oficinas a nuetras oficina",
    "video": "./assets/videos/recibir_pase_uno.mp4"
  },

  {
    "id": 2,
    "titulo": "REASIGNACION POR INCOMPETENCIA INFORMATIZADA",
    "categoria": "Masivos",
    "image": "./assets/img/video.png",
    "descripcion": "En este video se explica como reasignar una causa cuando viene por incompetencia de otro fuero, que utiliza el Sistema Lex-100",
    "video": "./assets/videos/recibir_pase_uno.mp4"
  },
  {
    "id": 3,
    "titulo": "REASIGNACION POR INCOMPETENCIA NO INFORMATIZADA",
    "categoria": "Masivos",
    "image": "./assets/img/video.png",
    "descripcion": "En este video se explica como reasignar una causa cuando viene por incompetencia de otro fuero, que NO utiliza el Sistema Lex-100",
    "video": "./assets/videos/recibir_pase_uno.mp4"
  },
  {
    "id": 4,
    "titulo": "REASIGNACION POR RECHAZO DE CONEXIDAD",
    "categoria": "Masivos",
    "image": "./assets/img/video.png",
    "descripcion": "En este video se explica como reasignar una causa cuando el juzgado asignado rechaza la conexidad automática",
    "video": "./assets/videos/recibir_pase_uno.mp4"
  },
  {
    "id": 5,
    "titulo": "REASIGNACION POR RECUSACION SIN CAUSA",
    "categoria": "Masivos",
    "image": "./assets/img/video.png",
    "descripcion": "En este video se explica como reasignar una causa cuando el juzgado da lugar a la Recusación sin causa",
    "video": "./assets/videos/recibir_pase_uno.mp4"
  },
  {
    "id": 6,
    "titulo": "REASIGNACION POR RECUSACION CON CAUSA",
    "categoria": "Masivos",
    "image": "./assets/img/video.png",
    "descripcion": "En este video se explica como reasignar una causa cuando el juzgado da lugar a la Recusación con causa",
    "video": "./assets/videos/recibir_pase_uno.mp4"
  },
  {
    "id": 7,
    "titulo": "REASIGNACION POR EXCUSACION",
    "categoria": "Masivos",
    "image": "./assets/img/video.png",
    "descripcion": "En este video se explica como reasignar una causa cuando el JUEZ se Excusa de seguir entendiendo en la causa",
    "video": "./assets/videos/recibir_pase_uno.mp4"
  },
  {
    "id": 8,
    "titulo": "HACER PASE DE EXPEDIENTE",
    "categoria": "Pases",
    "image": "./assets/img/video.png",
    "descripcion": "En este video se explica como hacer un pase de un expediente que tenemos que remitir a otra oficina",
    "video": "./assets/videos/recibir_pase_uno.mp4"
  },
  {
    "id": 9,
    "titulo": "CONFECCION DE DESPACHOS",
    "categoria": "Despachos",
    "image": "./assets/img/video.png",
    "descripcion": "En este video se explica como hacer un proyecto para confeccionar un despacho",
    "video": "./assets/videos/recibir_pase_uno.mp4"
  },
  {
    "id": 10,
    "titulo": "ELEVACIONES ABIERTAS - DESPACHO",
    "categoria": "Despachos",
    "image": "./assets/img/video.png",
    "descripcion": "En este video se explica que hacer en caso de que se encuentra abierta una elevacion de un expediente de otro fuero",
    "video": "./assets/videos/recibir_pase_uno.mp4"
  }
]
